roax/_schema.py
roax/cli.py
roax/context.py
roax/db.py
roax/file.py
roax/memory.py
roax/monitor.py
roax/openapi.py
roax/patch.py
roax/resource.py
roax/schema.py
roax/security.py
roax/sqlite.py
roax/static.py
roax/wsgi.py
roax-1.10.2.dist-info/LICENSE
roax-1.10.2.dist-info/WHEEL
roax-1.10.2.dist-info/METADATA
roax-1.10.2.dist-info/RECORD
