Metadata-Version: 2.1
Name: roax
Version: 1.10.2
Summary: Lightweight framework for building resource-oriented applications.
Home-page: https://github.com/roax/roax/
License: MIT
Keywords: wsgi,framework,resource,openapi
Author: Paul Bryan
Author-email: pbryan@anode.ca
Requires-Python: >=3.6,<4.0
Classifier: Development Status :: 5 - Production/Stable
Classifier: Intended Audience :: Developers
Classifier: License :: OSI Approved :: MIT License
Classifier: Programming Language :: Python :: 3
Classifier: Programming Language :: Python :: 3.6
Classifier: Programming Language :: Python :: 3.7
Classifier: Topic :: Internet :: WWW/HTTP :: WSGI :: Application
Requires-Dist: WebOb (>=1.8,<2.0)
Requires-Dist: isodate (>=0.6,<0.7)
Requires-Dist: wrapt (>=1.11,<2.0)
Project-URL: Documentation, https://github.com/roax/roax/tree/master/docs
